{"v":"5.6.10","fr":60,"ip":0,"op":210,"w":84,"h":84,"nm":"合成 1","ddd":0,"assets":[{"id":"image_0","w":60,"h":60,"u":"images/","p":"img_0.png","e":0},{"id":"image_1","w":60,"h":60,"u":"images/","p":"img_1.png","e":0},{"id":"image_2","w":84,"h":84,"u":"images/","p":"img_2.png","e":0},{"id":"comp_0","layers":[{"ddd":0,"ind":1,"ty":2,"nm":"叽叽.png","cl":"png","refId":"image_0","sr":1,"ks":{"o":{"a":0,"k":100,"ix":11},"r":{"a":0,"k":30,"ix":10},"p":{"a":1,"k":[{"i":{"x":0.667,"y":1},"o":{"x":0.333,"y":0},"t":30,"s":[48.933,270.817,0],"to":[5.028,-8.056,0],"ti":[-4.861,7.861,0]},{"i":{"x":0.667,"y":1},"o":{"x":0.333,"y":0},"t":50,"s":[79.1,222.483,0],"to":[4.861,-7.861,0],"ti":[0.167,-0.194,0]},{"i":{"x":0.667,"y":0.667},"o":{"x":0.333,"y":0.333},"t":60,"s":[78.1,223.65,0],"to":[0,0,0],"ti":[0,0,0]},{"i":{"x":0.667,"y":1},"o":{"x":0.333,"y":0},"t":80,"s":[78.1,223.65,0],"to":[0.167,-0.194,0],"ti":[4.861,-7.861,0]},{"i":{"x":0.667,"y":1},"o":{"x":0.333,"y":0},"t":90,"s":[79.1,222.483,0],"to":[-4.861,7.861,0],"ti":[5.028,-8.056,0]},{"t":110,"s":[48.933,270.817,0]}],"ix":2},"a":{"a":0,"k":[30,30,0],"ix":1},"s":{"a":0,"k":[100,100,100],"ix":6}},"ao":0,"ip":0,"op":300,"st":0,"bm":0},{"ddd":0,"ind":2,"ty":2,"nm":"哔哔.png","cl":"png","refId":"image_1","sr":1,"ks":{"o":{"a":0,"k":100,"ix":11},"r":{"a":0,"k":-30,"ix":10},"p":{"a":1,"k":[{"i":{"x":0.667,"y":1},"o":{"x":0.333,"y":0},"t":0,"s":[105.75,226,0],"to":[-0.056,-0.194,0],"ti":[-4.917,-7.306,0]},{"i":{"x":0.667,"y":1},"o":{"x":0.333,"y":0},"t":10,"s":[105.417,224.833,0],"to":[4.917,7.306,0],"ti":[-4.972,-7.5,0]},{"i":{"x":0.833,"y":0.833},"o":{"x":0.167,"y":0.167},"t":30,"s":[135.25,269.833,0],"to":[0,0,0],"ti":[0,0,0]},{"i":{"x":0.667,"y":1},"o":{"x":0.333,"y":0},"t":110,"s":[135.25,269.833,0],"to":[-4.972,-7.5,0],"ti":[4.917,7.306,0]},{"i":{"x":0.667,"y":1},"o":{"x":0.333,"y":0},"t":130,"s":[105.417,224.833,0],"to":[-4.917,-7.306,0],"ti":[-0.056,-0.194,0]},{"t":140,"s":[105.75,226,0]}],"ix":2},"a":{"a":0,"k":[30,30,0],"ix":1},"s":{"a":0,"k":[100,100,100],"ix":6}},"ao":0,"ip":0,"op":300,"st":0,"bm":0},{"ddd":0,"ind":3,"ty":4,"nm":"形状图层 1","sr":1,"ks":{"o":{"a":0,"k":100,"ix":11},"r":{"a":0,"k":0,"ix":10},"p":{"a":0,"k":[562.5,1218,0],"ix":2},"a":{"a":0,"k":[0,0,0],"ix":1},"s":{"a":0,"k":[100,100,100],"ix":6}},"ao":0,"shapes":[],"ip":0,"op":300,"st":0,"bm":0}]}],"layers":[{"ddd":0,"ind":1,"ty":0,"nm":"预合成 1","refId":"comp_0","sr":1,"ks":{"o":{"a":0,"k":100,"ix":11},"r":{"a":0,"k":0,"ix":10},"p":{"a":0,"k":[514.039,1050.039,0],"ix":2},"a":{"a":0,"k":[562.5,1218,0],"ix":1},"s":{"a":0,"k":[100,100,100],"ix":6}},"ao":0,"hasMask":true,"masksProperties":[{"inv":false,"mode":"a","pt":{"a":0,"k":{"i":[[23.174,0],[0,-23.174],[-23.174,0],[0,23.174]],"o":[[-23.174,0],[0,23.174],[23.174,0],[0,-23.174]],"v":[[89.961,168],[48,209.961],[89.961,251.922],[131.922,209.961]],"c":true},"ix":1},"o":{"a":0,"k":100,"ix":3},"x":{"a":0,"k":0,"ix":4},"nm":"蒙版 1"}],"w":1125,"h":2436,"ip":0,"op":300,"st":0,"bm":0},{"ddd":0,"ind":2,"ty":2,"nm":"白bg.png","cl":"png","refId":"image_2","sr":1,"ks":{"o":{"a":0,"k":100,"ix":11},"r":{"a":0,"k":0,"ix":10},"p":{"a":0,"k":[41.5,42,0],"ix":2},"a":{"a":0,"k":[42,42,0],"ix":1},"s":{"a":0,"k":[100,100,100],"ix":6}},"ao":0,"ip":0,"op":300,"st":0,"bm":0}],"markers":[]}